<window>

<!--
	The <resolution> tag is used for the setCoordinateResolution() function.
	
	You may move, add or delete any controls you want as long as they're not Required.
	With one exception, required controls <description> tag and <type> tag MUST NOT be changed.
	The exception is <type>label</type> may be changed to <type>button</type>.	This allows 
	<shadowcolor> tag to be used. (set <texturenofocus>-</texturenofocus> if doing this.)
		
	There are four special controls that are displayed based on if media is playing. You may set their
	tag <visible>false</visible> if you don't want them, but DO NOT delete them.
	
	<type>list</type> have an additional tag <hidespinner>, if set to true, a scrollbar will be used
	in place of the spinner control.
	
	<include> tags work and the defaults.xml file will be used for any missing tags.
	
	To use special images from the /gfx/ folder prepend a \. (eg <texture>\background.png</texture>)
	
-->

	<defaultcontrol always="true">10</defaultcontrol>
	<resolution>PAL16x9</resolution>
    <useincludes>false</useincludes>

	<controls>

		<control type="image" id="1">
			<description>background image</description>
			<posx>0</posx>
			<posy>0</posy>
			<width>720</width>
			<height>576</height>
			<texture>\background_16x9.png</texture>
		</control>

		<control type="label" id="1">
			<description>xbox media center label</description>
			<width>200</width>
			<posx>200</posx>
			<posy>63</posy>
			<align>right</align>
			<label>1</label>
			<font>special12</font>
			<textcolor>FFFFFFFF</textcolor>
		</control>

		<control type="image" id="1">
			<description>contentpanel slice</description>
			<posx>160</posx>
			<posy>108</posy>
			<width>64</width>
			<height>468</height>
			<texture>\contentpanel_left.png</texture>
		</control>

		<control type="image" id="1">
			<description>contentpanel slice</description>
			<posx>224</posx>
			<posy>108</posy>
			<width>500</width>
			<height>468</height>
			<texture>\contentpanel.png</texture>
		</control>

		<control type="image" id="1">
			<description>backdrop image categories</description>
			<posx>260</posx>
			<posy>130</posy>
			<width>375</width>
			<height>373</height>
			<aspectratio>keep</aspectratio>
			<texture>\backdrop.png</texture>
			<visible>Control.IsVisible(110)</visible> 
		</control>

		<control type="image" id="1">
			<description>backdrop image trailers</description>
			<posx>231</posx>
			<posy>115</posy>
			<width>250</width>
			<height>250</height>
			<aspectratio>keep</aspectratio>
			<texture>\backdrop.png</texture>
			<visible>Control.IsVisible(100)</visible> 
		</control>

		<!-- labels -->
		
		<!-- ** Required ** Do not change <description> -->
		<control type="label" id="1">
			<description>Title Label</description>
			<width>200</width>
			<posx>207</posx>
			<posy>63</posy>
			<align>left</align>
			<label>0</label>
			<font>special13</font>
			<textcolor>FFFFFFFF</textcolor>
		</control>

		<!-- ** Required ** Do not change <description> -->
		<control type="label" id="1">
			<description>Category Label</description>
			<posx>650</posx>
			<posy>63</posy>
			<width>300</width>
			<height>35</height>
			<align>right</align>
			<label>-</label>
			<font>special13</font>
			<textcolor>FFFFFFFF</textcolor>
		</control>
		
		<!-- Buttons -->

		<!-- ** Required ** Do not change <description> or <type> -->
		<control type="button" id="10">
			<description>Shortcut1 Button</description>
			<label>-</label>
			<posx>50</posx>
			<posy>120</posy>
			<width>150</width>
			<height>33</height>
			<texturefocus>\button-focus.png</texturefocus>
			<texturenofocus>\button-nofocus.png</texturenofocus>
			<font>font13</font>
			<textcolor>FFFFFFFF</textcolor>
			<disabledcolor>60ffffff</disabledcolor>
			<textoffsetx>17</textoffsetx>
			<aligny>center</aligny>
			<onleft>95</onleft>
			<onright>100</onright>
			<onup>70</onup>
			<ondown>20</ondown>
			<onclick>-</onclick>
		</control>

		<!-- ** Required ** Do not change <description> or <type> -->
		<control type="button" id="20">
			<description>Shortcut2 Button</description>
			<label>-</label>
			<posx>50</posx>
			<posy>157</posy>
			<width>150</width>
			<height>33</height>
			<texturefocus>\button-focus.png</texturefocus>
			<texturenofocus>\button-nofocus.png</texturenofocus>
			<font>font13</font>
			<textcolor>FFFFFFFF</textcolor>
			<disabledcolor>60ffffff</disabledcolor>
			<textoffsetx>17</textoffsetx>
			<aligny>center</aligny>
			<onleft>95</onleft>
			<onright>100</onright>
			<onup>10</onup>
			<ondown>30</ondown>
			<onclick>-</onclick>
		</control>

		<!-- ** Required ** Do not change <description> or <type> -->
		<control type="button" id="30">
			<description>Shortcut3 Button</description>
			<label>-</label>
			<posx>50</posx>
			<posy>194</posy>
			<width>150</width>
			<height>33</height>
			<texturefocus>\button-focus.png</texturefocus>
			<texturenofocus>\button-nofocus.png</texturenofocus>
			<font>font13</font>
			<textcolor>FFFFFFFF</textcolor>
			<disabledcolor>60ffffff</disabledcolor>
			<textoffsetx>17</textoffsetx>
			<aligny>center</aligny>
			<onleft>95</onleft>
			<onright>100</onright>
			<onup>20</onup>
			<ondown>40</ondown>
			<onclick>-</onclick>
		</control>

		<!-- ** Required ** Do not change <description> or <type> -->
		<control type="button" id="40">
			<description>Genre Button</description>
			<label>103</label>
			<posx>50</posx>
			<posy>264</posy>
			<width>150</width>
			<height>33</height>
			<texturefocus>\button-focus.png</texturefocus>
			<texturenofocus>\button-nofocus.png</texturenofocus>
			<font>font13</font>
			<textcolor>FFFFFFFF</textcolor>
			<disabledcolor>60ffffff</disabledcolor>
			<textoffsetx>17</textoffsetx>
			<aligny>center</aligny>
			<onleft>95</onleft>
			<onright>100</onright>
			<onup>30</onup>
			<ondown>45</ondown>
			<onclick>-</onclick>
		</control>
		
        <!-- ** Required ** Do not change <description> or <type> -->
		<control type="button" id="45">
			<description>Studio Button</description>
			<label>104</label>
			<posx>50</posx>
			<posy>301</posy>
			<width>150</width>
			<height>33</height>
			<texturefocus>\button-focus.png</texturefocus>
			<texturenofocus>\button-nofocus.png</texturenofocus>
			<font>font13</font>
			<textcolor>FFFFFFFF</textcolor>
			<disabledcolor>60ffffff</disabledcolor>
			<textoffsetx>17</textoffsetx>
			<aligny>center</aligny>
			<onleft>95</onleft>
			<onright>100</onright>
			<onup>40</onup>
			<ondown>50</ondown>
			<onclick>-</onclick>
		</control>
		
		<!-- ** Required ** Do not change <description> or <type> -->
		<control type="button" id="50">
			<description>Actor Button</description>
			<label>105</label>
			<posx>50</posx>
			<posy>338</posy>
			<width>150</width>
			<height>33</height>
			<texturefocus>\button-focus.png</texturefocus>
			<texturenofocus>\button-nofocus.png</texturenofocus>
			<font>font13</font>
			<textcolor>FFFFFFFF</textcolor>
			<disabledcolor>60ffffff</disabledcolor>
			<textoffsetx>17</textoffsetx>
			<aligny>center</aligny>
			<onleft>95</onleft>
			<onright>100</onright>
			<onup>45</onup>
			<ondown>60</ondown>
			<onclick>-</onclick>
		</control>
		
		<!-- ** Required ** Do not change <description> or <type> -->
		<control type="button" id="60">
			<description>Search Button</description>
			<label>106</label>
			<posx>50</posx>
			<posy>408</posy>
			<width>150</width>
			<height>33</height>
			<texturefocus>\button-focus.png</texturefocus>
			<texturenofocus>\button-nofocus.png</texturenofocus>
			<font>font13</font>
			<textcolor>FFFFFFFF</textcolor>
			<disabledcolor>60ffffff</disabledcolor>
			<textoffsetx>17</textoffsetx>
			<aligny>center</aligny>
			<onleft>95</onleft>
			<onright>100</onright>
			<onup>50</onup>
			<ondown>70</ondown>
			<onclick>-</onclick>
		</control>

		<!-- ** Required ** Do not change <description> or <type> -->
		<control type="button" id="70">
			<description>Settings Button</description>
			<label>107</label>
			<posx>50</posx>
			<posy>478</posy>
			<width>150</width>
			<height>33</height>
			<texturefocus>\button-focus.png</texturefocus>
			<texturenofocus>\button-nofocus.png</texturenofocus>
			<font>font13</font>
			<textcolor>FFFFFFFF</textcolor>
			<disabledcolor>60ffffff</disabledcolor>
			<textoffsetx>17</textoffsetx>
			<aligny>center</aligny>
			<onleft>95</onleft>
			<onright>100</onright>
			<onup>60</onup>
			<ondown>10</ondown>
			<onclick>-</onclick>
		</control>

        <!-- 
            Uncomment the following control and uncomment the pair of <label> and <onclick> you prefer 
            and add them to the control. Don't forget to adjust you <on*> tags.
        -->
			<!--label>154</label>
			<onclick>self.updateScript()</onclick-->
			<!--label>155</label
			<onclick>self.showCredits()</onclick-->

		<!-- ** Optional ** Do not change <description> or <type> -->
		<!--control type="button" id="80">
			<description>Optional Button</description>
			<label>154</label>
			<onclick>self.updateScript()</onclick>
            <posx>50</posx>
			<posy>517</posy>
			<width>150</width>
			<height>33</height>
			<texturefocus>\button-focus.png</texturefocus>
			<texturenofocus>\button-nofocus.png</texturenofocus>
			<font>font13</font>
			<textcolor>FFFFFFFF</textcolor>
			<disabledcolor>60ffffff</disabledcolor>
			<textoffsetx>17</textoffsetx>
			<aligny>center</aligny>
			<onleft>95</onleft>
			<onright>100</onright>
			<onup>70</onup>
			<ondown>10</ondown>
		</control-->

		<!-- Trailer list controls -->
		
		<!-- ** Optional w/ all Trailer List Scrollbar controls ** Do not change <description> or <type> -->
		<control type="image" id="1">
			<description>Trailer List Scrollbar Up Arrow</description>
			<posx>502</posx>
			<posy>121</posy>
			<width>12</width>
			<height>16</height>
			<texture>\scrollbar-up-arrow.png</texture>
			<visible allowhiddenfocus="false">Control.IsVisible(100)</visible> 
		</control>

		<!-- ** Optional w/ all Trailer List Scrollbar controls ** Do not change <description> or <type> -->
		<control type="image" id="1">
			<description>Trailer List Scrollbar Middle</description>
			<posx>502</posx>
			<posy>137</posy>
			<width>12</width>
			<height>201</height>
			<texture>\scrollbar-middle.png</texture>
			<visible allowhiddenfocus="false">Control.IsVisible(100)</visible> 
		</control>
		
		<!-- ** Optional w/ all Trailer List Scrollbar controls ** Do not change <description> or <type> -->
		<control type="image" id="1">
			<description>Trailer List Scrollbar Down Arrow</description>
			<posx>502</posx>
			<posy>338</posy>
			<width>12</width>
			<height>16</height>
			<texture>\scrollbar-down-arrow.png</texture>
			<visible allowhiddenfocus="false">Control.IsVisible(100)</visible> 
		</control>
		
		<!-- ** Optional w/ all Trailer List Scrollbar controls ** Do not change <description> or <type> -->
		<control type="button" id="900">
			<description>Trailer List Scrollbar Position Indicator</description>
			<label>-</label>
			<posx>502</posx>
			<posy>137</posy>
			<width>12</width>
			<height>16</height>
			<texturefocus>\scrollbar-indicator-focus.png</texturefocus>
			<texturenofocus>\scrollbar-indicator-nofocus.png</texturenofocus>
			<font>font13</font>
			<textcolor>00FFFFFF</textcolor>
			<shadowcolor>00FFFFFF</shadowcolor>
			<disabledcolor>00ffffff</disabledcolor>
			<textoffsetx>17</textoffsetx>
			<aligny>center</aligny>
			<onleft>110</onleft>
			<onright>91</onright>
			<onup>900</onup>
			<ondown>900</ondown>
			<onclick>-</onclick>
			<visible allowhiddenfocus="false">Control.IsVisible(100)</visible> 
		</control>

		<!-- ** Optional ** Do not change <description> -->
		<control type="list" id="0">
			<description>Trailer List Backdrop</description>
			<font>font13</font>
			<posx>211</posx>
			<posy>121</posy>
			<width>290</width>
			<height>260</height>
			<textcolor>00FFFFFF</textcolor>
			<selectedcolor>FFFFFF00</selectedcolor>
			<textureup>\scroll-up.png</textureup>
			<texturedown>\scroll-down.png</texturedown>
			<textureupfocus>\scroll-up-focus.png</textureupfocus>
			<texturedownfocus>\scroll-down-focus.png</texturedownfocus>
			<texturefocus>-</texturefocus>
			<texturenofocus>\list-nofocus.png</texturenofocus>
			<textureheight>26</textureheight>
			<itemwidth>10</itemwidth>
			<itemheight>22</itemheight>
			<hidespinner>true</hidespinner>
			<spacebetweenitems>0</spacebetweenitems>
			<image>-</image>
			<textxoff>3</textxoff>
			<suffix>|</suffix>
			<aligny>center</aligny>
			<label> </label>
			<label> </label>
			<label> </label>
			<label> </label>
			<label> </label>
			<label> </label>
			<label> </label>
			<label> </label>
			<label> </label>
			<visible allowhiddenfocus="false">Control.IsVisible(100)</visible> 
		</control>
		
		<!-- ** Required ** Do not change <description> or <type> -->
		<control type="list" id="100">
			<description>Trailer List</description>
			<font>font13</font>
			<posx>211</posx>
			<posy>121</posy>
			<width>290</width>
			<height>260</height>
			<textcolor>FFFFFFFF</textcolor>
			<selectedcolor>FFFFFF00</selectedcolor>
			<textureup>\scroll-up.png</textureup>
			<texturedown>\scroll-down.png</texturedown>
			<textureupfocus>\scroll-up-focus.png</textureupfocus>
			<texturedownfocus>\scroll-down-focus.png</texturedownfocus>
			<texturefocus>\list-focus2.png</texturefocus>
			<texturenofocus>-</texturenofocus>
			<textureheight>26</textureheight>
			<itemwidth>10</itemwidth>
			<itemheight>22</itemheight>
			<hidespinner>true</hidespinner>
			<spacebetweenitems>0</spacebetweenitems>
			<image>-</image>
			<textxoff>3</textxoff>
			<suffix>|</suffix>
			<aligny>center</aligny>
			<onup>100</onup>
			<ondown>100</ondown>
			<onleft>10</onleft>
			<onright>110</onright>
			<visible>false</visible>
		</control>

		<!-- ** Required ** Do not change <description> -->
		<control type="label" id="1">
			<description>Trailer List Count Label</description>
			<width>100</width>
			<posx>500</posx>
			<posy>355</posy>
			<align>right</align>
			<label>-</label>
			<font>font10</font>
			<textcolor>CCFFFFFF</textcolor>
			<visible allowhiddenfocus="false">Control.IsVisible(100)</visible> 
		</control>

		<!-- Category list controls -->
		
		<!-- ** Optional w/ all Category List Scrollbar controls ** Do not change <description> or <type> -->
		<control type="image" id="1">
			<description>Category List Scrollbar Up Arrow</description>
			<posx>657</posx>
			<posy>121</posy>
			<width>12</width>
			<height>16</height>
			<texture>\scrollbar-up-arrow.png</texture>
			<visible allowhiddenfocus="false">Control.IsVisible(110)</visible> 
		</control>

		<!-- ** Optional w/ all Category List Scrollbar controls ** Do not change <description> or <type> -->
		<control type="image" id="1">
			<description>Category List Scrollbar Middle</description>
			<posx>657</posx>
			<posy>137</posy>
			<width>12</width>
			<height>357</height>
			<texture>\scrollbar-middle.png</texture>
			<visible allowhiddenfocus="false">Control.IsVisible(110)</visible> 
		</control>
		
		<!-- ** Optional w/ all Category List Scrollbar controls ** Do not change <description> or <type> -->
		<control type="image" id="1">
			<description>Category List Scrollbar Down Arrow</description>
			<posx>657</posx>
			<posy>494</posy>
			<width>12</width>
			<height>16</height>
			<texture>\scrollbar-down-arrow.png</texture>
			<visible allowhiddenfocus="false">Control.IsVisible(110)</visible> 
		</control>
		
		<!-- ** Optional w/ all Category List Scrollbar controls ** Do not change <description> or <type> -->
		<control type="button" id="91">
			<description>Category List Scrollbar Position Indicator</description>
			<label>-</label>
			<posx>657</posx>
			<posy>137</posy>
			<width>12</width>
			<height>16</height>
			<texturefocus>\scrollbar-indicator-focus.png</texturefocus>
			<texturenofocus>\scrollbar-indicator-nofocus.png</texturenofocus>
			<font>font13</font>
			<textcolor>00FFFFFF</textcolor>
			<shadowcolor>00FFFFFF</shadowcolor>
			<disabledcolor>00ffffff</disabledcolor>
			<textoffsetx>17</textoffsetx>
			<aligny>center</aligny>
			<onleft>900</onleft>
			<onright>210</onright>
			<onup>91</onup>
			<ondown>91</ondown>
			<onclick>-</onclick>
			<visible allowhiddenfocus="false">Control.IsVisible(110)</visible> 
		</control>

		<!-- ** Optional ** Do not change <description> -->
		<control type="list" id="0">
			<description>Category List Backdrop</description>
			<font>font13</font>
			<posx>211</posx>
			<posy>121</posy>
			<width>445</width>
			<height>425</height>
			<textcolor>FFFFFFFF</textcolor>
			<selectedcolor>d0ffffff</selectedcolor>
			<textureup>\scroll-up.png</textureup>
			<texturedown>\scroll-down.png</texturedown>
			<textureupfocus>\scroll-up-focus.png</textureupfocus>
			<texturedownfocus>\scroll-down-focus.png</texturedownfocus>
			<texturefocus>-</texturefocus>
			<texturenofocus>\list-nofocus.png</texturenofocus>
			<textureheight>26</textureheight>
			<itemwidth>22</itemwidth>
			<itemheight>22</itemheight>
			<hidespinner>true</hidespinner>
			<spacebetweenitems>0</spacebetweenitems>
			<image>-</image>
			<textxoff>3</textxoff>
			<suffix>|</suffix>
			<aligny>center</aligny>
			<label> </label>
			<label> </label>
			<label> </label>
			<label> </label>
			<label> </label>
			<label> </label>
			<label> </label>
			<label> </label>
			<label> </label>
			<label> </label>
			<label> </label>
			<label> </label>
			<label> </label>
			<label> </label>
			<label> </label>
			<visible allowhiddenfocus="false">Control.IsVisible(110)</visible> 
		</control>

		<!-- ** Required ** Do not change <description> or <type> -->
		<control type="list" id="110">
			<description>Category List</description>
			<font>font13</font>
			<posx>211</posx>
			<posy>121</posy>
			<width>445</width>
			<height>425</height>
			<textcolor>FFFFFFFF</textcolor>
			<selectedcolor>d0ffffff</selectedcolor>
			<textureup>\scroll-up.png</textureup>
			<texturedown>\scroll-down.png</texturedown>
			<textureupfocus>\scroll-up-focus.png</textureupfocus>
			<texturedownfocus>\scroll-down-focus.png</texturedownfocus>
			<texturefocus>\list-focus2.png</texturefocus>
			<texturenofocus>-</texturenofocus>
			<textureheight>26</textureheight>
			<itemwidth>22</itemwidth>
			<itemheight>22</itemheight>
			<hidespinner>true</hidespinner>
			<spacebetweenitems>0</spacebetweenitems>
			<image>-</image>
			<textxoff>3</textxoff>
			<suffix>|</suffix>
			<aligny>center</aligny>
			<onup>110</onup>
			<ondown>110</ondown>
			<onleft>100</onleft>
			<onright>900</onright>
			<visible>false</visible>
		</control>

		<!-- ** Required ** Do not change <description> -->
		<control type="label" id="1">
			<description>Category List Count Label</description>
			<width>100</width>
			<posx>655</posx>
			<posy>520</posy>
			<align>right</align>
			<label>-</label>
			<font>font10</font>
			<textcolor>CCFFFFFF</textcolor>
			<visible allowhiddenfocus="false">Control.IsVisible(110)</visible> 
		</control>

		<!-- info controls -->
		
		<!-- ** Optional ** -->
		<control type="image" id="200">
			<description>Poster Backdrop</description>
			<posx>518</posx>
			<posy>118</posy>
			<width>174</width>
			<height>254</height>
			<texture>\poster_backdrop.png</texture>
			<aspectratio>keep</aspectratio>
			<visible allowhiddenfocus="false">Control.IsVisible(100)</visible> 
		</control>

		<!-- ** Required ** Do not change <description> or <type> -->
		<control type="image" id="201">
			<description>Trailer Poster</description>
			<posx>520</posx>
			<posy>120</posy>
			<width>170</width>
			<height>250</height>
			<texture>-</texture>
			<aspectratio>keep</aspectratio>
			<visible allowhiddenfocus="false">Control.IsVisible(100)</visible> 
		</control>

		<!-- ** Required ** Do not change <description> or <type> -->
		<control type="image" id="202">
			<description>Trailer Rating</description>
			<posx>540</posx>
			<posy>350</posy>
			<width>66</width>
			<height>15</height>
			<texture>-</texture>
			<aspectratio>keep</aspectratio>
			<visible allowhiddenfocus="false">Control.IsVisible(100)</visible> 
		</control>

		<!-- ** Required ** Do not change <description> or <type> -->
		<control type="image" id="203">
			<description>Trailer Favorite Overlay</description>
			<posx>645</posx>
			<posy>350</posy>
			<width>16</width>
			<height>16</height>
			<texture>\overlay-favorite.png</texture>
			<aspectratio>keep</aspectratio>
			<visible allowhiddenfocus="false">Control.IsVisible(100)</visible> 
		</control>

		<!-- ** Required ** Do not change <description> or <type> -->
		<control type="image" id="204">
			<description>Trailer Watched Overlay</description>
			<posx>645</posx>
			<posy>350</posy>
			<width>16</width>
			<height>16</height>
			<texture>\overlay-watched.png</texture>
			<aspectratio>keep</aspectratio>
			<visible allowhiddenfocus="false">Control.IsVisible(100)</visible> 
		</control>

		<!-- ** Required ** Do not change <description> or <type> -->
		<control type="image" id="205">
			<description>Trailer Saved Overlay</description>
			<posx>645</posx>
			<posy>350</posy>
			<width>16</width>
			<height>16</height>
			<texture>\overlay-saved.png</texture>
			<aspectratio>keep</aspectratio>
			<visible allowhiddenfocus="false">Control.IsVisible(100)</visible> 
		</control>

		<!-- ** Required ** Do not change <description> -->
		<control type="label" id="206">
			<description>Trailer Title</description>
			<width>400</width>
			<posx>240</posx>
			<posy>375</posy>
			<align>left</align>
			<label>-</label>
			<font>special13</font>
			<textcolor>FFFFFFFF</textcolor>
			<visible allowhiddenfocus="false">Control.IsVisible(100)</visible> 
		</control>
		
		<!-- ** Required ** Do not change <description> or <type> -->
		<control type="button" id="210">
			<description>Plot Button</description>
			<label>215</label>
			<posx>211</posx>
			<posy>370</posy>
			<width>24</width>
			<height>32</height>
			<texturefocus>\plot-button-focus.png</texturefocus>
			<texturenofocus>\plot-button-nofocus.png</texturenofocus>
			<font>font13</font>
			<textcolor>00FFFFFF</textcolor>
			<shadowcolor>00FFFFFF</shadowcolor>
			<disabledcolor>60ffffff</disabledcolor>
			<textoffsetx>17</textoffsetx>
			<align>center</align>
			<aligny>center</aligny>
			<onleft>91</onleft>
			<onright>211</onright>
			<onup>100</onup>
			<ondown>216</ondown>
			<visible allowhiddenfocus="false">!Control.IsVisible(110)</visible> 
			<onclick>-</onclick>
		</control>

		<!-- ** Required ** Do not change <description> or <type> -->
		<control type="button" id="211">
			<description>Cast Button</description>
			<label>216</label>
			<posx>211</posx>
			<posy>370</posy>
			<width>24</width>
			<height>32</height>
			<texturefocus>\cast-button-focus.png</texturefocus>
			<texturenofocus>\cast-button-nofocus.png</texturenofocus>
			<font>font13</font>
			<textcolor>00FFFFFF</textcolor>
			<shadowcolor>00FFFFFF</shadowcolor>
			<disabledcolor>60ffffff</disabledcolor>
			<textoffsetx>17</textoffsetx>
			<align>center</align>
			<aligny>center</aligny>
			<onleft>210</onleft>
			<onright>215</onright>
			<onup>100</onup>
			<ondown>215</ondown>
			<visible allowhiddenfocus="false">!Control.IsVisible(110)</visible> 
			<onclick>-</onclick>
		</control>
		
		<!-- ** Required ** Do not change <description> or <type> -->
		<control type="textbox" id="215">
			<description>Trailer Plot</description>
			<posx>211</posx>
			<posy>407</posy>
			<width>445</width>
			<height>142</height>
			<font>font12</font>
			<textcolor>FFFFFFFF</textcolor>
			<onup>215</onup>
			<ondown>215</ondown>
			<onleft>211</onleft>
			<onright>216</onright>
			<textureup>\scroll-up.png</textureup>
			<texturedown>\scroll-down.png</texturedown>
			<textureupfocus>\scroll-up-focus.png</textureupfocus>
			<texturedownfocus>\scroll-down-focus.png</texturedownfocus>
			<visible allowhiddenfocus="false">Control.IsVisible(211)</visible> 
		</control>

		<!-- ** Optional w/ all Cast List Scrollbar controls ** Do not change <description> or <type> -->
		<control type="image" id="1">
			<description>Cast List Scrollbar Up Arrow</description>
			<posx>647</posx>
			<posy>403</posy>
			<width>12</width>
			<height>16</height>
			<texture>\scrollbar-up-arrow.png</texture>
			<visible allowhiddenfocus="false">Control.IsVisible(210)</visible> 
		</control>

		<!-- ** Optional w/ all Cast List Scrollbar controls ** Do not change <description> or <type> -->
		<control type="image" id="1">
			<description>Cast List Scrollbar Middle</description>
			<posx>647</posx>
			<posy>419</posy>
			<width>12</width>
			<height>71</height>
			<texture>\scrollbar-middle.png</texture>
			<visible allowhiddenfocus="false">Control.IsVisible(210)</visible> 
		</control>
		
		<!-- ** Optional w/ all Cast List Scrollbar controls ** Do not change <description> or <type> -->
		<control type="image" id="1">
			<description>Cast List Scrollbar Down Arrow</description>
			<posx>647</posx>
			<posy>490</posy>
			<width>12</width>
			<height>16</height>
			<texture>\scrollbar-down-arrow.png</texture>
			<visible allowhiddenfocus="false">Control.IsVisible(210)</visible> 
		</control>
		
		<!-- ** Optional w/ all Cast List Scrollbar controls ** Do not change <description> or <type> -->
		<control type="button" id="95">
			<description>Cast List Scrollbar Position Indicator</description>
			<label>-</label>
			<posx>647</posx>
			<posy>419</posy>
			<width>12</width>
			<height>16</height>
			<texturefocus>\scrollbar-indicator-focus.png</texturefocus>
			<texturenofocus>\scrollbar-indicator-nofocus.png</texturenofocus>
			<font>font13</font>
			<textcolor>00FFFFFF</textcolor>
			<shadowcolor>00FFFFFF</shadowcolor>
			<disabledcolor>00ffffff</disabledcolor>
			<textoffsetx>17</textoffsetx>
			<aligny>center</aligny>
			<onleft>216</onleft>
			<onright>10</onright>
			<onup>95</onup>
			<ondown>95</ondown>
			<onclick>-</onclick>
			<visible allowhiddenfocus="false">Control.IsVisible(210)</visible> 
		</control>

		<!-- ** Optional ** Do not change <description> -->
		<control type="list" id="0">
			<description>Cast List Backdrop</description>
			<posx>211</posx>
			<posy>403</posy>
			<width>435</width>
			<height>135</height>
			<font>font12</font>
			<textcolor>00FFFFFF</textcolor>
			<textureup>\scroll-up.png</textureup>
			<texturedown>\scroll-down.png</texturedown>
			<textureupfocus>\scroll-up-focus.png</textureupfocus>
			<texturedownfocus>\scroll-down-focus.png</texturedownfocus>
			<texturefocus>-</texturefocus>
			<texturenofocus>\list-nofocus.png</texturenofocus>
			<textureheight>26</textureheight>
			<itemwidth>16</itemwidth>
			<itemheight>22</itemheight>
			<hidespinner>true</hidespinner>
			<spacebetweenitems>0</spacebetweenitems>
			<visible allowhiddenfocus="false">Control.IsVisible(210)</visible> 
			<label> </label>
			<label> </label>
			<label> </label>
			<label> </label>
		</control>

		<!-- ** Required ** Do not change <description> or <type> -->
		<control type="list" id="216">
			<description>Cast List</description>
			<posx>211</posx>
			<posy>403</posy>
			<width>435</width>
			<height>135</height>
			<font>font12</font>
			<textcolor>FFFFFFFF</textcolor>
			<onup>216</onup>
			<ondown>216</ondown>
			<onleft>215</onleft>
			<onright>95</onright>
			<textureup>\scroll-up.png</textureup>
			<texturedown>\scroll-down.png</texturedown>
			<textureupfocus>\scroll-up-focus.png</textureupfocus>
			<texturedownfocus>\scroll-down-focus.png</texturedownfocus>
			<texturefocus>\list-focus2.png</texturefocus>
			<texturenofocus>-</texturenofocus>
			<textureheight>26</textureheight>
			<itemwidth>16</itemwidth>
			<itemheight>22</itemheight>
			<hidespinner>true</hidespinner>
			<spacebetweenitems>0</spacebetweenitems>
			<visible allowhiddenfocus="false">Control.IsVisible(210)</visible> 
		</control>

	</controls>

</window>
